{
  "adjectives": {
    "16": [
      "Absolute", "Boundless", "Colossal", "Cosmic", "Eternal", "Fundamental",
      "Infinite", "Interstellar", "Limitless", "Paramount", "Primordial", "Universal",
      "Ultimate", "Vast", "Celestial", "Omnipotent", "Singular", "Supreme",
      "Immeasurable", "Transcendent", "Omniversal", "Immutable", "Perpetual", "Timeless",
      "Encompassing", "All-Pervading", "Superlative", "Archetypal", "Essential", "Perfect"
    ],
    "32": [
      "Abundant", "Ascending", "Binding", "Dynamic", "Endless", "Fundamental",
      "Grand", "Hyperion", "Imperial", "Majestic", "Sovereign", "Stellar",
      "Sublime", "Unified", "Dominant", "Mammoth", "Massive",
      "Towering", "Regal", "Magnificent", "Colossal", "Gigantic", "Commanding",
      "Overwhelming", "Imposing", "Monumental", "Formidable", "Glorious", "Mighty"
    ],
    "48": [
      "Abundant", "Clustered", "Collective", "Connected", "Flowing", "Gathering",
      "Harmonious", "Linked", "Networked", "Streaming", "Unified", "United",
      "Woven", "Bound", "Converging", "Joined",
      "Interwoven", "Synchronized", "Orchestrated", "Collaborative", "Interlinked", "Cascading",
      "Resonant", "Symbiotic", "Coordinated", "Integrated", "Merged", "Bridged"
    ],
    "64": [
      "Astral", "Blazing", "Brilliant", "Luminous", "Nebulous", "Radiant",
      "Shining", "Spiraling", "Stellar", "Swirling", "Whirling", "Rotating",
      "Galactic", "Cosmic", "Starborn", "Celestial",
      "Iridescent", "Gleaming", "Incandescent", "Prismatic", "Phosphorescent", "Opalescent",
      "Coruscating", "Effervescent", "Lustrous", "Pearlescent", "Shimmering", "Scintillant"
    ],
    "80": [
      "Burning", "Flaring", "Gleaming", "Glowing", "Golden", "Illuminated",
      "Lucent", "Pulsing", "Radiating", "Scintillating", "Twinkling", "Bright",
      "Dazzling", "Effulgent", "Starlit",
      "Blazing", "Flickering", "Smoldering", "Flashing", "Beaming", "Glimmering",
      "Sparkling", "Lambent", "Luminescent", "Coruscant", "Refulgent", "Candescent"
    ],
    "96": [
      "Balanced", "Circular", "Gravitational", "Harmonious", "Orbital", "Planetary",
      "Revolving", "Solar", "Synchronous", "Systematic", "Aligned", "Cyclic",
      "Ecliptic", "Ordered",
      "Elliptical", "Perihelion", "Aphelion", "Heliocentric", "Centripetal", "Rotational",
      "Meridional", "Celestial", "Equatorial", "Polar", "Axial", "Geodetic"
    ],
    "112": [
      "Azure", "Crystalline", "Emerald", "Frozen", "Gaseous", "Molten",
      "Obsidian", "Rocky", "Sapphire", "Terrestrial", "Tropical", "Verdant",
      "Violet", "Volcanic", "Windswept", "Crimson",
      "Amber", "Cerulean", "Titanium", "Cobalt", "Platinum", "Diamond",
      "Onyx", "Jade", "Ruby", "Opal", "Quartz", "Granite", "Basalt", "Marble"
    ],
    "128": [
      "Ancient", "Bustling", "Colonial", "Fortified", "Hidden", "Industrial",
      "Metropolitan", "Noble", "Prosperous", "Rising", "Sacred", "Thriving",
      "Urban", "Vibrant", "Wealthy", "Established",
      "Majestic", "Peaceful", "Advanced", "Historic", "Cultural", "Artistic",
      "Scientific", "Commercial", "Residential", "Academic", "Diplomatic", "Ceremonial"
    ]
  },
  "nouns": {
    "16": [
      "Axis", "Boundary", "Expanse", "Firmament", "Infinity", "Matrix",
      "Membrane", "Nexus", "Singularity", "Terminus", "Vector", "Vertex",
      "Void", "Web", "Fabric", "Lattice", "Framework"
    ],
    "32": [
      "Amalgam", "Bastion", "Colossus", "Domain", "Empire", "Formation",
      "Legion", "Mandate", "Realm", "Sphere", "Supremacy", "Unity",
      "Dominion", "Coalition", "Assembly"
    ],
    "48": [
      "Assembly", "Chain", "Confluence", "Fellowship", "Network", "Pattern",
      "Sequence", "Stream", "Symphony", "Union", "Weave", "Collection",
      "Gathering", "Association"
    ],
    "64": [
      "Corona", "Cosmos", "Disk", "Eye", "Helix", "Nebula",
      "Spiral", "Star", "Vortex", "Whirlpool", "Ring", "Cloud",
      "Field", "Sea", "Cluster"
    ],
    "80": [
      "Beacon", "Constellation", "Crucible", "Ember", "Flame", "Forge",
      "Light", "Pyre", "Spark", "Torch", "Aurora", "Flare",
      "Stream", "Garden"
    ],
    "96": [
      "Circuit", "Cycle", "Horizon", "Orbit", "Path", "Procession",
      "Ring", "Sanctuary", "Sphere", "System", "Dance", "Family",
      "Haven", "Domain"
    ],
    "112": [
      "Globe", "Haven", "Heart", "Keep", "Oasis", "Paradise",
      "Sanctuary", "Sphere", "Stronghold", "Vale", "World", "Garden",
      "Realm", "Crown", "Jewel"
    ],
    "128": [
      "Arcology", "Citadel", "Enclave", "Fortress", "Haven", "Nexus",
      "Outpost", "Sanctuary", "Spire", "Stronghold", "Tower", "Ward",
      "Capital", "Port", "Station", "Hub"
    ]
  },
  "celestialTypes": {
    "16": [
      "Superstructure", "Cosmic Wall", "Great Wall", "Filament",
      "Cosmic Web", "Void Wall", "Megastructure", "Cosmic Ring",
      "Barrier", "Cosmic Membrane", "Universal Divide"
    ],
    "32": [
      "Supercluster", "Galaxy Shell", "Cosmic Shell", "Massive Cluster",
      "Meta Cluster", "Celestial Complex", "Cosmic Cloud", "Stellar Sea"
    ],
    "48": [
      "Galaxy Group", "Star Cluster", "Stellar Association",
      "Galactic Cloud", "Cosmic Stream", "Celestial Chain",
      "Stellar Complex", "Galactic Gathering"
    ],
    "64": [
      "Galaxy", "Nebula", "Star Sea", "Stellar Spiral",
      "Cosmic Disk", "Star Cloud", "Stellar Field", "Galactic Ring"
    ],
    "80": [
      "Star Group", "Stellar Cluster", "Star Stream", "Star Field",
      "Cosmic Oasis", "Stellar Neighborhood", "Star Colony", "Stellar Circuit"
    ],
    "96": [
      "Solar System", "Star System", "Planetary System", "Stellar Domain",
      "Cosmic Haven", "Star Domain", "Stellar Sanctuary", "Orbital Realm"
    ],
    "112": [
      "Planet", "Celestial Body", "World", "Planetoid",
      "Moon", "Satellite", "Giant Moon", "Megamoon",
      "Dwarf Planet", "Minor Planet", "Ice Giant", "Gas Giant"
    ],
    "128": [
      "Metropolis", "City", "Megacity", "Habitat",
      "Colony", "Settlement", "Outpost", "Station",
      "Enclave", "Base", "Community", "Urban Center",
      "Village", "Town", "Borough", "District"
    ]
  },
  "subnetMappings": {
    "0": 16,
    "1": 32,
    "2": 48,
    "3": 64,
    "4": 80,
    "5": 96,
    "6": 112,
    "7": 128
  },
  "levelNames": [
    "Great Wall",
    "Supercluster",
    "Galaxy Group",
    "Galaxy",
    "Star Cluster",
    "Solar System",
    "Planet",
    "City"
  ]
}